Metadata-Version: 2.1
Name: thermoencoder
Version: 0.1.2
Summary: Thermometer Encoding for ordinal variables
Home-page: http://github.com/kmedian/thermoencoder
Author: Ulf Hamster
Author-email: 554c46@gmail.com
License: MIT
Platform: UNKNOWN
Requires-Python: >=3.6
